LICENSE.txt
LICENSE_SUPPLEMENTAL_DISCLAIMER.txt
MANIFEST.in
NOTICES.txt
README.rst
setup.cfg
setup.py
versioneer.py
cdpcli/__init__.py
cdpcli/_version.py
cdpcli/argparser.py
cdpcli/argprocess.py
cdpcli/arguments.py
cdpcli/auth.py
cdpcli/cdprequest.py
cdpcli/clicommand.py
cdpcli/clidriver.py
cdpcli/client.py
cdpcli/compat.py
cdpcli/completer.py
cdpcli/configloader.py
cdpcli/credentials.py
cdpcli/docs.py
cdpcli/endpoint.py
cdpcli/exceptions.py
cdpcli/formatter.py
cdpcli/help.py
cdpcli/loader.py
cdpcli/main.py
cdpcli/model.py
cdpcli/paginate.py
cdpcli/paramfile.py
cdpcli/parser.py
cdpcli/retryhandler.py
cdpcli/schema.py
cdpcli/serialize.py
cdpcli/shorthand.py
cdpcli/signers.py
cdpcli/table.py
cdpcli/text.py
cdpcli/textwriter.py
cdpcli/translate.py
cdpcli/utils.py
cdpcli/validate.py
cdpcli.egg-info/PKG-INFO
cdpcli.egg-info/SOURCES.txt
cdpcli.egg-info/dependency_links.txt
cdpcli.egg-info/entry_points.txt
cdpcli.egg-info/requires.txt
cdpcli.egg-info/top_level.txt
cdpcli/data/_retry.json
cdpcli/data/aliases.yaml
cdpcli/data/cli.json
cdpcli/data/datahub/datahub.yaml
cdpcli/data/datalake/datalake.yaml
cdpcli/data/environments/environments.yaml
cdpcli/data/iam/iam.yaml
cdpcli/data/ml/ml.yaml
cdpcli/doc/__init__.py
cdpcli/doc/docstringparser.py
cdpcli/doc/restdoc.py
cdpcli/doc/style.py
cdpcli/examples/configure/_description.rst
cdpcli/examples/configure/get/_description.rst
cdpcli/examples/configure/get/_examples.rst
cdpcli/examples/configure/set/_description.rst
cdpcli/examples/configure/set/_examples.rst
cdpcli/examples/dataeng/submit-jobs.rst
cdpcli/extensions/__init__.py
cdpcli/extensions/arguments.py
cdpcli/extensions/cliinputjson.py
cdpcli/extensions/commands.py
cdpcli/extensions/generatecliskeleton.py
cdpcli/extensions/paginate.py
cdpcli/extensions/writer.py
cdpcli/extensions/configure/__init__.py
cdpcli/extensions/configure/configure.py
cdpcli/extensions/configure/get.py
cdpcli/extensions/configure/list.py
cdpcli/extensions/configure/set.py
cdpcli/thirdparty/__init__.py
cdpcli/thirdparty/six.py
cdpcli/thirdparty/requests/__init__.py
cdpcli/thirdparty/requests/adapters.py
cdpcli/thirdparty/requests/api.py
cdpcli/thirdparty/requests/auth.py
